Metadata-Version: 2.1
Name: privacypanda
Version: 0.1.0
Summary: Anonymizing pandas dataframes
Home-page: https://github.com/TTitcombe/PrivacyPanda
Author: Tom Titcombe
Author-email: t.j.titcombe@gmail.com
License: Apache 2.0
Keywords: anonymization privacy pandas privacy-preserving data science
Platform: UNKNOWN
Classifier: License :: OSI Approved :: Apache Software License
Classifier: Programming Language :: Python :: 3
Classifier: Topic :: Scientific/Engineering :: Information Analysis
Classifier: Topic :: Security
Requires-Python: >=3.7
